setup.py
dsp_distributions/Binomialdistribution.py
dsp_distributions/Gaussiandistribution.py
dsp_distributions/Generaldistribution.py
dsp_distributions/__init__.py
dsp_distributions.egg-info/PKG-INFO
dsp_distributions.egg-info/SOURCES.txt
dsp_distributions.egg-info/dependency_links.txt
dsp_distributions.egg-info/not-zip-safe
dsp_distributions.egg-info/top_level.txt