Metadata-Version: 1.0
Name: dsp-distributions
Version: 0.1
Summary: Gaussian distributions
Home-page: UNKNOWN
Author: David Stefan Pedemonte
Author-email: david@pedemonte.net
License: UNKNOWN
Platform: UNKNOWN
